pyfiller/__config__.py
pyfiller/__init__.py
pyfiller/common.py
pyfiller/pyfiller.py
pyFiller-1.0.2.dist-info/LICENSE
pyFiller-1.0.2.dist-info/METADATA
pyFiller-1.0.2.dist-info/WHEEL
pyFiller-1.0.2.dist-info/entry_points.txt
pyFiller-1.0.2.dist-info/top_level.txt
pyFiller-1.0.2.dist-info/RECORD
