Metadata-Version: 2.1
Name: pyFiller
Version: 1.0.2
Summary: A tool that literally takes up space
Home-page: https://github.com/MartinFalatic/pyfiller
Author: Martin F. Falatic
Author-email: martin@falatic.com
License: MIT License
Keywords: filesystem wipe filler generator
Platform: UNKNOWN
Classifier: License :: OSI Approved :: MIT License
Classifier: Intended Audience :: Developers
Classifier: Topic :: Utilities
Classifier: Programming Language :: Python :: 3.6
Classifier: Programming Language :: Python :: 3.7
Classifier: Programming Language :: Python :: 3.8
Classifier: Development Status :: 5 - Production/Stable
Requires-Dist: colorama
Requires-Dist: humanfriendly
Requires-Dist: tqdm
